pytch/__init__.py
pytch/__main__.py
pytch/art.py
pytch/funcs.py
pytch_fetch-1.2.3.dist-info/COPYING
pytch_fetch-1.2.3.dist-info/METADATA
pytch_fetch-1.2.3.dist-info/WHEEL
pytch_fetch-1.2.3.dist-info/entry_points.txt
pytch_fetch-1.2.3.dist-info/top_level.txt
pytch_fetch-1.2.3.dist-info/RECORD
